{
  "UNMODELING": {
    "ENAMEL": {
      "NAME": "Краска антикоррозионная, покрытие в два слоя. Расход - 0.2 кг на м²",
      "MARK": "БТ-177",
      "CODE": "",
      "CREATOR": "",
      "UNIT": "кг"
    },
    "PRIMER": {
      "NAME": "Грунтовка для стальных труб, покрытие в один слой. Расход - 0.1 кг на м²",
      "MARK": "ГФ-031",
      "CODE": "",
      "CREATOR": "",
      "UNIT": "кг"
    }
  },
  "UNMODELING_CONFIG": {
    "config_001": {
      "CONFIG_NAME": "Эмаль",
      "CATEGORY": "-2008044",
      "GROUP": "99_Краски",
      "NAME": "Краска антикоррозионная, покрытие в два слоя. Расход - 0.2 кг на м²",
      "MARK": "",
      "CODE": "",
      "UNIT": "кг",
      "CREATOR": "",
      "VALUE_FORMULA": "Area * 0.2 * 2",
      "NOTE_FORMAT": "sumArea м², площадь за раз",
      "ASSIGNED_ELEMENT_IDS": [],
      "USE_CATEGORY_RESERVE": true
    },
    "config_002": {
      "CONFIG_NAME": "Грунтовка",
      "CATEGORY": "-2008044",
      "GROUP": "99_Краски",
      "NAME": "Грунтовка для стальных труб, покрытие в один слой. Расход - 0.1 кг на м²",
      "MARK": "ГФ-031",
      "CODE": "",
      "UNIT": "кг",
      "CREATOR": "",
      "VALUE_FORMULA": "Area * 0.1",
      "NOTE_FORMAT": "sumArea м², площадь за раз",
      "ASSIGNED_ELEMENT_IDS": [],
      "USE_CATEGORY_RESERVE": true
    },
    "config_003": {
      "CONFIG_NAME": "Металл для воздуховодов",
      "CATEGORY": "-2008000",
      "GROUP": "99_Крепления",
      "NAME": "Металлические крепления для воздуховодов",
      "MARK": "",
      "CODE": "",
      "UNIT": "кг",
      "CREATOR": "",
      "VALUE_FORMULA": "Perimeter < 1001 ? Area * 0.65 : Perimeter < 1801 ? Area * 1.22 : Area * 2.25",
      "NOTE_FORMAT": "",
      "ASSIGNED_ELEMENT_IDS": [],
      "USE_CATEGORY_RESERVE": true
    },
    "config_004": {
      "CONFIG_NAME": "Металл для трубопроводов",
      "CATEGORY": "-2008044",
      "GROUP": "99_Крепления",
      "NAME": "Металлические крепления для трубопроводов",
      "MARK": "",
      "CODE": "",
      "UNIT": "кг",
      "CREATOR": "",
      "VALUE_FORMULA": "(Diameter <= 15 ? 0.238 : Diameter <= 20 ? 0.204 : Diameter <= 25 ? 0.187 : Diameter <= 32 ? 0.170 : Diameter <= 40 ? 0.187 : Diameter <= 50 ? 0.2448 : Diameter <= 65 ? 0.3315 : Diameter <= 80 ? 0.3791 : Diameter <= 100 ? 0.629 : Diameter <= 125 ? 0.901 : Diameter <= 150 ? 1.054 : Diameter <= 200 ? 1.309 : 0.1564) * Length/1000",
      "NOTE_FORMAT": "",
      "ASSIGNED_ELEMENT_IDS": [],
      "USE_CATEGORY_RESERVE": true
    },
    "config_005": {
      "CONFIG_NAME": "Хомут трубный под шпильку М8",
      "CATEGORY": "-2008044",
      "GROUP": "99_Хомуты и шпильки",
      "NAME": "Хомут трубный под шпильку М8",
      "MARK": "",
      "CODE": "",
      "UNIT": "шт.",
      "CREATOR": "",
      "VALUE_FORMULA": "Length < 0.5 ? 0 : (Diameter <= 15 ? (IsInsulated ? 1.5 : 2) : Diameter <= 20 ? (IsInsulated ? 2 : 3) : Diameter <= 25 ? (IsInsulated ? 2 : 3.5) : Diameter <= 32 ? (IsInsulated ? 2.5 : 4) : Diameter <= 40 ? (IsInsulated ? 3 : 4.5) : Diameter <= 50 ? (IsInsulated ? 3 : 5) : Diameter <= 65 ? (IsInsulated ? 4 : 6) : Diameter <= 80 ? (IsInsulated ? 4 : 6) : Diameter <= 100 ? (IsInsulated ? 4.5 : 6) : Diameter <= 125 ? (IsInsulated ? 5 : 7) : (IsInsulated ? 5 : 7)) * Length",
      "NOTE_FORMAT": "",
      "ASSIGNED_ELEMENT_IDS": [],
      "USE_CATEGORY_RESERVE": true
    },
    "config_006": {
      "CONFIG_NAME": "Шпилька М8 1м/1шт",
      "CATEGORY": "-2008044",
      "GROUP": "99_Хомуты и шпильки",
      "NAME": "Шпилька М8 1м/1шт",
      "MARK": "",
      "CODE": "",
      "UNIT": "шт.",
      "CREATOR": "",
      "VALUE_FORMULA": "Length < 0.5 ? 0 : (Diameter <= 15 ? (IsInsulated ? 1.5 : 2) : Diameter <= 20 ? (IsInsulated ? 2 : 3) : Diameter <= 25 ? (IsInsulated ? 2 : 3.5) : Diameter <= 32 ? (IsInsulated ? 2.5 : 4) : Diameter <= 40 ? (IsInsulated ? 3 : 4.5) : Diameter <= 50 ? (IsInsulated ? 3 : 5) : Diameter <= 65 ? (IsInsulated ? 4 : 6) : Diameter <= 80 ? (IsInsulated ? 4 : 6) : Diameter <= 100 ? (IsInsulated ? 4.5 : 6) : Diameter <= 125 ? (IsInsulated ? 5 : 7) : (IsInsulated ? 5 : 7)) * Length",
      "NOTE_FORMAT": "",
      "ASSIGNED_ELEMENT_IDS": [],
      "USE_CATEGORY_RESERVE": true
    },
    "config_007": {
      "CONFIG_NAME": "Комплекты заделки для трубопроводов",
      "NAME": "Комплекты заделки для трубопроводов",
      "CATEGORY": "-2008043",
      "GROUP": "99_Комплекты заделки",
      "MARK": "",
      "CODE": "",
      "UNIT": "шт",
      "CREATOR": "",
      "VALUE_FORMULA": "1",
      "NOTE_FORMAT": "",
      "ASSIGNED_ELEMENT_IDS": [],
      "USE_CATEGORY_RESERVE": true
    },
    "config_008": {
      "CONFIG_NAME": "Фреон для жидкостной линии",
      "NAME": "Фреон",
      "CATEGORY": "-2008044",
      "GROUP": "99_Расходники",
      "MARK": "",
      "CODE": "",
      "UNIT": "м3",
      "CREATOR": "",
      "VALUE_FORMULA": "SystemTypeName == \"Фреон_Жидкость\" ? Volume : 0",
      "NOTE_FORMAT": "",
      "ASSIGNED_ELEMENT_IDS": [],
      "USE_CATEGORY_RESERVE": true
    }
  },
  "UNMODELING_SETTINGS": {
    "ONLY_PROJECT_INSTANCES": true
  }
}
